cgexplore/__init__.py
cgexplore/_version.py
cgexplore/analysis.py
cgexplore/atomistic.py
cgexplore/forcefields.py
cgexplore/molecular.py
cgexplore/optimisation.py
cgexplore/scram.py
cgexplore/systems_optimisation.py
cgexplore/terms.py
cgexplore/topologies.py
cgexplore/utilities.py
cgexplore/_internal/__init__.py
cgexplore/_internal/analysis/__init__.py
cgexplore/_internal/analysis/geom.py
cgexplore/_internal/analysis/shape.py
cgexplore/_internal/atomistic/__init__.py
cgexplore/_internal/atomistic/crest_process.py
cgexplore/_internal/atomistic/utilities.py
cgexplore/_internal/forcefields/__init__.py
cgexplore/_internal/forcefields/assigned_system.py
cgexplore/_internal/forcefields/forcefield.py
cgexplore/_internal/forcefields/martini.py
cgexplore/_internal/forcefields/utilities.py
cgexplore/_internal/molecular/__init__.py
cgexplore/_internal/molecular/beads.py
cgexplore/_internal/molecular/conformer.py
cgexplore/_internal/molecular/ensembles.py
cgexplore/_internal/molecular/molecule_construction.py
cgexplore/_internal/molecular/precursor_generator.py
cgexplore/_internal/molecular/utilities.py
cgexplore/_internal/optimisation/__init__.py
cgexplore/_internal/optimisation/openmm_optimizer.py
cgexplore/_internal/scram/__init__.py
cgexplore/_internal/scram/building_block_enum.py
cgexplore/_internal/scram/construction.py
cgexplore/_internal/scram/enumeration.py
cgexplore/_internal/scram/topology_code.py
cgexplore/_internal/scram/utilities.py
cgexplore/_internal/scram/known_graphs/g_10P20.json
cgexplore/_internal/scram/known_graphs/g_1P2.json
cgexplore/_internal/scram/known_graphs/g_2P4.json
cgexplore/_internal/scram/known_graphs/g_3P6.json
cgexplore/_internal/scram/known_graphs/g_4P8.json
cgexplore/_internal/scram/known_graphs/g_6P12.json
cgexplore/_internal/scram/known_graphs/g_8P16.json
cgexplore/_internal/scram/known_graphs/rx_10P20.json
cgexplore/_internal/scram/known_graphs/rx_11P22.json
cgexplore/_internal/scram/known_graphs/rx_12P24.json
cgexplore-2025.2.5.1.dist-info/LICENSE
cgexplore-2025.2.5.1.dist-info/METADATA
cgexplore-2025.2.5.1.dist-info/WHEEL
cgexplore-2025.2.5.1.dist-info/entry_points.txt
cgexplore-2025.2.5.1.dist-info/top_level.txt
cgexplore-2025.2.5.1.dist-info/RECORD
