Metadata-Version: 2.2
Name: cgexplore
Version: 2025.2.5.1
Maintainer-email: Andrew Tarzia <andrew.tarzia@gmail.com>
Project-URL: github, https://github.com/andrewtarzia/CGExplore
Requires-Python: >=3.11
License-File: LICENSE
Requires-Dist: scipy
Requires-Dist: matplotlib
Requires-Dist: pandas
Requires-Dist: scikit-learn
Requires-Dist: stk
Requires-Dist: stko
Requires-Dist: atomlite
Requires-Dist: chemiscope>0.7.3
Requires-Dist: rustworkx
Requires-Dist: bbprepared
Provides-Extra: dev
Requires-Dist: ruff; extra == "dev"
Requires-Dist: mypy; extra == "dev"
Requires-Dist: pip-tools; extra == "dev"
Requires-Dist: pytest<8; extra == "dev"
Requires-Dist: pytest-datadir; extra == "dev"
Requires-Dist: pytest-lazy-fixture; extra == "dev"
Requires-Dist: pytest-cov; extra == "dev"
Requires-Dist: sphinx; extra == "dev"
Requires-Dist: sphinx-copybutton; extra == "dev"
Requires-Dist: twine; extra == "dev"
Requires-Dist: sphinx_rtd_theme; extra == "dev"
Requires-Dist: furo; extra == "dev"
